README.rst
setup.cfg
setup.py
django_cloud_tasks/__init__.py
django_cloud_tasks/apps.py
django_cloud_tasks/base.py
django_cloud_tasks/connection.py
django_cloud_tasks/constants.py
django_cloud_tasks/decorators.py
django_cloud_tasks/registries.py
django_cloud_tasks/urls.py
django_cloud_tasks/views.py
django_cloud_tasks_withcredentials.egg-info/PKG-INFO
django_cloud_tasks_withcredentials.egg-info/SOURCES.txt
django_cloud_tasks_withcredentials.egg-info/dependency_links.txt
django_cloud_tasks_withcredentials.egg-info/not-zip-safe
django_cloud_tasks_withcredentials.egg-info/requires.txt
django_cloud_tasks_withcredentials.egg-info/top_level.txt