Metadata-Version: 1.1
Name: django-cloud-tasks-withcredentials
Version: 0.0.4
Summary: Google Cloud Tasks integration for Django. Forked from https://github.com/GeorgeLubaretsi/django-cloud-tasks
Home-page: https://github.com/rgutierrez-cotech/django-cloud-tasks
Author: rgutierrez-cotech
Author-email: gutierrez@carnegiehub.org
License: MIT
Download-URL: https://github.com/rgutierrez-cotech/django-cloud-tasks/archive/0.0.4a.tar.gz
Keywords: django cloudtasks cloud tasks
Platform: UNKNOWN
Classifier: Framework :: Django
Classifier: Framework :: Django :: 1.11
Classifier: Framework :: Django :: 2.0
Classifier: Intended Audience :: Developers
Classifier: License :: OSI Approved :: BSD License
Classifier: Natural Language :: English
Classifier: Programming Language :: Python :: 3
Classifier: Programming Language :: Python :: 3.4
Classifier: Programming Language :: Python :: 3.5
Classifier: Programming Language :: Python :: 3.6
